soft_delete/__init__.py
soft_delete/admin.py
soft_delete/models.py
soft_delete_t-1.0.3.dist-info/LICENSE
soft_delete_t-1.0.3.dist-info/METADATA
soft_delete_t-1.0.3.dist-info/WHEEL
soft_delete_t-1.0.3.dist-info/top_level.txt
soft_delete_t-1.0.3.dist-info/RECORD
